re_plugin_pack/__init__.py
re_plugin_pack/plugins/date_normalizer.py
re_plugin_pack/plugins/drafts.py
re_plugin_pack/plugins/latest_entries.py
re_plugin_pack/plugins/next_prev.py
re_plugin_pack-2025.6.1.dist-info/licenses/LICENSE.md
re_plugin_pack-2025.6.1.dist-info/WHEEL
re_plugin_pack-2025.6.1.dist-info/METADATA
re_plugin_pack-2025.6.1.dist-info/RECORD
