Metadata-Version: 2.4
Name: re-plugin-pack
Version: 2025.6.1
Summary: Plugin pack for render-engine static site generator
Author: Dan Shernicoff
Author-email: Dan Shernicoff <dan@brassnet.biz>
License-Expression: MIT
License-File: LICENSE.md
Requires-Dist: render-engine>=2025.6.1
Requires-Python: >=3.10
Project-URL: Repository, https://github.com/brass75/re-plugin-pack
Project-URL: homepage, https://github.com/brass75/re-plugin-pack
